autotimebar/__init__.py
autotimebar/_version.py
ipy_autotimebar-0.0.2.dist-info/LICENSE
ipy_autotimebar-0.0.2.dist-info/METADATA
ipy_autotimebar-0.0.2.dist-info/WHEEL
ipy_autotimebar-0.0.2.dist-info/top_level.txt
ipy_autotimebar-0.0.2.dist-info/RECORD
