Metadata-Version: 2.1
Name: ipy-autotimebar
Version: 0.0.2
Summary: Extend autotime to use in jupyter notebooks time bar per cell.
Home-page: https://github.com/alien3211/ipy-autotimebar
Author: Alan Tetich
Author-email: alan.tetich.project@gmail.com
License: Apache
Platform: UNKNOWN
Classifier: Environment :: Console
Classifier: Intended Audience :: Developers
Classifier: Intended Audience :: Science/Research
Classifier: Intended Audience :: Education
Classifier: License :: OSI Approved :: Apache Software License
Classifier: Operating System :: OS Independent
Classifier: Programming Language :: Python
Classifier: Topic :: Scientific/Engineering
Classifier: Topic :: Utilities
License-File: LICENSE
Requires-Dist: ipython
Requires-Dist: ipywidgets
Requires-Dist: monotonic ; python_version < "3.3"
